l5k/__init__.py
l5k/aoi.py
l5k/aoi.py~
l5k/builtin.py
l5k/controller.py
l5k/datatype.py
l5k/grammar.py
l5k/program.py
l5k/tag.py
l5k-0.2.dist-info/METADATA
l5k-0.2.dist-info/WHEEL
l5k-0.2.dist-info/licenses/LICENSE.txt
l5k-0.2.dist-info/RECORD
