Metadata-Version: 2.4
Name: l5k
Version: 0.2
Summary: Logix 5000 L5K parser.
Project-URL: Homepage, https://github.com/jvalenzuela/l5k
Project-URL: Repository, https://github.com/jvalenzuela/l5k.git
Project-URL: Issues, https://github.com/jvalenzuela/l5k/issues
Author: Jason Valenzuela
Author-email: jvalenzuela1977@gmail.com
License: BSD 3-Clause License
License-File: LICENSE.txt
Classifier: Environment :: Console
Classifier: License :: OSI Approved :: BSD License
Classifier: Operating System :: OS Independent
Classifier: Programming Language :: Python :: 3
Classifier: Programming Language :: Python :: 3 :: Only
Classifier: Programming Language :: Python :: 3.10
Classifier: Programming Language :: Python :: 3.11
Classifier: Programming Language :: Python :: 3.12
Classifier: Programming Language :: Python :: 3.13
Classifier: Topic :: Text Processing
Requires-Python: <3.14,>=3.10
Requires-Dist: pyparsing
